README.md
setup.py
generic_design_patterns/__init__.py
generic_design_patterns/chain.py
generic_design_patterns/event.py
generic_design_patterns/exception.py
generic_design_patterns/log.py
generic_design_patterns/plugin.py
generic_design_patterns/specification.py
generic_design_patterns.egg-info/PKG-INFO
generic_design_patterns.egg-info/SOURCES.txt
generic_design_patterns.egg-info/dependency_links.txt
generic_design_patterns.egg-info/requires.txt
generic_design_patterns.egg-info/top_level.txt