Metadata-Version: 2.1
Name: generic-design-patterns
Version: 1.1.10
Summary: Python package implements design patterns in generic way. Its can be used in a wide range of projects.
Home-page: https://github.com/ShadowCodeCz/generic_design_patterns
Author: ShadowCodeCz
Author-email: shadow.code.cz@gmail.com
License: GNU Affero General Public License v3 or later (AGPLv3+)
Project-URL: Source, https://github.com/ShadowCodeCz/generic_design_patterns
Project-URL: Tracker, https://github.com/ShadowCodeCz/generic_design_patterns/issues
Keywords: design patterns event chain specification
Platform: UNKNOWN
Classifier: Development Status :: 5 - Production/Stable
Classifier: Intended Audience :: Developers
Classifier: Programming Language :: Python :: 2.7
Classifier: Programming Language :: Python :: 3.4
Classifier: Programming Language :: Python :: 3.5
Classifier: Programming Language :: Python :: 3.6
Classifier: Programming Language :: Python :: 3.7
Classifier: Programming Language :: Python :: 3.8
Classifier: Programming Language :: Python :: 3.9
Classifier: License :: OSI Approved :: GNU Affero General Public License v3 or later (AGPLv3+)
Classifier: Operating System :: OS Independent
